[
  {
    "id": 1,
    "nombre": "Tomate",
    "precio": 2000,
    "unidad": "kg",
    "imagen": "/productos/tomate.jpg"
  },
  {
    "id": 2,
    "nombre": "Lechuga",
    "precio": 1500,
    "unidad": "unidad",
    "imagen": "/productos/lechuga.jpg"
  },
  {
    "id": 3,
    "nombre": "Zanahoria",
    "precio": 2500,
    "unidad": "unidad",
    "imagen": "/productos/lechuga.jpg"
  },
  {
    "id": 4,
    "nombre": "Manzana",
    "precio": 700,
    "unidad": "unidad",
    "imagen": "/productos/lechuga.jpg"
  }
]
